MzmcOSAPIPySDK/__init__.py
MzmcOSAPIPySDK/ecvg.py
MzmcOSAPIPySDK/ecwg.py
MzmcOSAPIPySDK/info.py
MzmcOSAPIPySDK/player.py
MzmcOSAPIPySDK/request.py
MzmcOSAPIPySDK/user.py
mzmcosapipysdk-1.4.1.dist-info/METADATA
mzmcosapipysdk-1.4.1.dist-info/WHEEL
mzmcosapipysdk-1.4.1.dist-info/top_level.txt
mzmcosapipysdk-1.4.1.dist-info/RECORD
